{
  "reportMaster": [
    {
      "masterSelectionWiseReport": true
    }
  ],
  "company": [
    {
      "id": 1,
      "name": "SigmaGlobal"
    },
    {
      "id": 2,
      "name": "BetaTech"
    },
    {
      "id": 3,
      "name": "LambdaSoft"
    },
    {
      "id": 4,
      "name": "SigmaLabs"
    },
    {
      "id": 5,
      "name": "OmicronLabs"
    },
    {
      "id": 6,
      "name": "DeltaGlobal"
    }
  ],
  "department": [
    {
      "id": 1,
      "name": "R&D"
    },
    {
      "id": 2,
      "name": "Support"
    },
    {
      "id": 3,
      "name": "HR"
    },
    {
      "id": 4,
      "name": "IT"
    },
    {
      "id": 5,
      "name": "Finance"
    },
    {
      "id": 6,
      "name": "Design"
    }
  ],
  "master_UserJob": [
    {
      "id": 1,
      "userJob": "100"
    },
    {
      "id": 2,
      "userJob": "200"
    },
    {
      "id": 3,
      "userJob": "300"
    },
    {
      "id": 4,
      "userJob": "400"
    },
    {
      "id": 5,
      "userJob": "500"
    },
    {
      "id": 6,
      "userJob": "600"
    },
    {
      "id": 7,
      "userJob": "700"
    },
    {
      "id": 8,
      "userJob": "800"
    },
    {
      "id": 9,
      "userJob": "900"
    },
    {
      "id": 10,
      "userJob": "1000"
    }
  ],
  "master_Amount": [
    {
      "id": 1,
      "amount": "1000"
    },
    {
      "id": 2,
      "amount": "2000"
    },
    {
      "id": 3,
      "amount": "3000"
    },
    {
      "id": 4,
      "amount": "4000"
    },
    {
      "id": 5,
      "amount": "5000"
    },
    {
      "id": 6,
      "amount": "6000"
    },
    {
      "id": 7,
      "amount": "7000"
    },
    {
      "id": 8,
      "amount": "8000"
    },
    {
      "id": 9,
      "amount": "9000"
    },
    {
      "id": 10,
      "amount": "10000"
    }
  ]
}
